COPYING
LICENSE
MANIFEST.in
README.org
setup.py
./__init__.py
./server.py
./transceiver.py
mongrel2_transceiver.egg-info/PKG-INFO
mongrel2_transceiver.egg-info/SOURCES.txt
mongrel2_transceiver.egg-info/dependency_links.txt
mongrel2_transceiver.egg-info/requires.txt
mongrel2_transceiver.egg-info/top_level.txt