Metadata-Version: 1.1
Name: mongrel2-transceiver
Version: 0.3.0
Summary: Non-blocking Mongrel2 handler transceiver
Home-page: https://github.com/webheroesinc/transilience
Author: Matthew Brisebois
Author-email: matthew@webheroes.ca
License: Dual License; GPLv3 and Proprietary
Keywords: mongrel2,zmq,transceiver,websocket,http
Platform: UNKNOWN
Classifier: License :: OSI Approved :: GNU General Public License v3 or later (GPLv3+)
Classifier: License :: Other/Proprietary License
Classifier: Programming Language :: Python :: 2.7
Classifier: Development Status :: 4 - Beta
Classifier: Intended Audience :: Developers
